mkdocs_multisource_docs/__init__.py
mkdocs_multisource_docs/plugin.py
mkdocs_multisource_docs/src/__init__.py
mkdocs_multisource_docs/src/config.py
mkdocs_multisource_docs/src/constants.py
mkdocs_multisource_docs/src/corpus_manager.py
mkdocs_multisource_docs/src/gitlab_utils.py
mkdocs_multisource_docs/src/logs.py
mkdocs_multisource_docs/src/main.py
mkdocs_multisource_docs/src/md_utils.py
mkdocs_multisource_docs/src/utils.py
mkdocs_multisource_docs/src/builders/__init__.py
mkdocs_multisource_docs/src/builders/javadoc.py
mkdocs_multisource_docs-0.1.2.dist-info/licenses/LICENSE
mkdocs_multisource_docs-0.1.2.dist-info/METADATA
mkdocs_multisource_docs-0.1.2.dist-info/WHEEL
mkdocs_multisource_docs-0.1.2.dist-info/entry_points.txt
mkdocs_multisource_docs-0.1.2.dist-info/top_level.txt
mkdocs_multisource_docs-0.1.2.dist-info/RECORD
