Metadata-Version: 2.4
Name: mkdocs-multisource-docs
Version: 0.1.2
Summary: A MkDocs plugin that is designed to automate the process of collecting documentation from multiple GitLab repositories and integrating it into the documentation of the current repository.
Author-email: Dmitry Uraev <uraev.dima@yandex.ru>
License: MIT License
Classifier: Development Status :: 3 - Alpha
Classifier: Intended Audience :: Developers
Classifier: Intended Audience :: Information Technology
Classifier: Intended Audience :: System Administrators
Classifier: License :: OSI Approved :: MIT License
Classifier: Programming Language :: Python :: 3.10
Classifier: Programming Language :: Python :: 3.11
Classifier: Programming Language :: Python :: 3.12
Classifier: Topic :: Documentation
Classifier: Topic :: Software Development :: Documentation
Classifier: Topic :: Utilities
Requires-Python: >=3.10
License-File: LICENSE
Requires-Dist: mkdocs>=1.5.3
Requires-Dist: python-gitlab>=4.4.0
Requires-Dist: pydantic>=2.10.6
Dynamic: license-file
